.bumpversion.cfg
.coveragerc
.travis.yml
LICENSE
README.rst
requirements.tx
setup.cfg
setup.py
tox.ini
docs/Makefile
docs/adapter.rst
docs/conf.py
docs/exception.rst
docs/guide.rst
docs/index.rst
docs/types.rst
parameter/__init__.py
parameter/adapter.py
parameter/exception.py
parameter/model.py
parameter/types.py
parameter.egg-info/PKG-INFO
parameter.egg-info/SOURCES.txt
parameter.egg-info/dependency_links.txt
parameter.egg-info/not-zip-safe
parameter.egg-info/pbr.json
parameter.egg-info/top_level.txt
tests/__init__.py
tests/test_adapter.py
tests/test_model.py
tests/test_types.py