Metadata-Version: 1.1
Name: parameter
Version: 0.0.3.dev2
Summary: "Get and check HTTP parameters like ORM."
Home-page: https://github.com/coldnight/parameter
Author: Gray King
Author-email: grayking.w@gmail.com
License: Apache 2.0
Platform: UNKNOWN
Classifier: Topic :: Internet
Classifier: Development Status :: 2 - Pre-Alpha
Classifier: Intended Audience :: Developers
Classifier: Natural Language :: Chinese (Simplified)
Classifier: License :: OSI Approved :: Apache Software License
Classifier: Programming Language :: Python :: 2.7
Classifier: Programming Language :: Python :: 3.3
Classifier: Programming Language :: Python :: 3.4
Classifier: Programming Language :: Python :: 3.5
Classifier: Programming Language :: Python :: 3.6
